rotem.py
rotem-0.1.1.dist-info/licenses/LICENSE
rotem-0.1.1.dist-info/METADATA
rotem-0.1.1.dist-info/WHEEL
rotem-0.1.1.dist-info/top_level.txt
rotem-0.1.1.dist-info/RECORD
