Metadata-Version: 2.4
Name: rotem
Version: 0.1.1
Summary: a simple python library used to draw text-based 2d grid game map and informations
Author-email: PrinceBiscuit <redsawbiscuit@gmail.com>
Project-URL: Homepage, https://github.com/529324416/rotem
Keywords: tui,terminal,pypi
Classifier: Development Status :: 3 - Alpha
Classifier: Intended Audience :: Developers
Classifier: License :: OSI Approved :: MIT License
Classifier: Programming Language :: Python :: 3
Classifier: Programming Language :: Python :: 3.7
Classifier: Programming Language :: Python :: 3.8
Classifier: Programming Language :: Python :: 3.9
Classifier: Programming Language :: Python :: 3.10
Classifier: Programming Language :: Python :: 3.11
License-File: LICENSE
Dynamic: license-file
